.DS_Store
hfhd/__init__.py
hfhd/hd.py
hfhd/hf.py
hfhd/loss.py
hfhd/sim.py
hfhd-0.1.4.dist-info/LICENSE.txt
hfhd-0.1.4.dist-info/METADATA
hfhd-0.1.4.dist-info/WHEEL
hfhd-0.1.4.dist-info/top_level.txt
hfhd-0.1.4.dist-info/RECORD
