Metadata-Version: 2.1
Name: hfhd
Version: 0.1.4
Summary: hfhd is an accelerated Python library for estimating (integrated) covariance matrices with high frequency data in high dimensions.
Home-page: https://github.com/jpwoeltjen/hfhd
Author: Jan Philipp Woeltjen
Author-email: j.p.woeltjen@gmail.com
License: MIT
Project-URL: Documentation, https://hfhd.readthedocs.io/en/latest/
Project-URL: Issues, https://github.com/jpwoeltjen/hfhd/issues
Platform: UNKNOWN
Classifier: License :: OSI Approved :: MIT License
Classifier: Programming Language :: Python
Classifier: Programming Language :: Python :: 3
Classifier: Programming Language :: Python :: 3.6
Classifier: Programming Language :: Python :: Implementation :: CPython
Classifier: Programming Language :: Python :: Implementation :: PyPy
Requires-Python: >=3.6.0
Requires-Dist: numpy
Requires-Dist: pandas
Requires-Dist: numba
Requires-Dist: seaborn
Provides-Extra: dev
Requires-Dist: pytest (>=5.0) ; extra == 'dev'
Provides-Extra: docs
Requires-Dist: Sphinx (==3.0.3) ; extra == 'docs'
Requires-Dist: sphinx-automodapi (==0.12) ; extra == 'docs'
Requires-Dist: sphinx-math-dollar (==1.1.1) ; extra == 'docs'
Requires-Dist: sphinxcontrib-devhelp (==1.0.2) ; extra == 'docs'
Requires-Dist: sphinxcontrib-htmlhelp (==1.0.3) ; extra == 'docs'
Requires-Dist: sphinxcontrib-jsmath (==1.0.1) ; extra == 'docs'
Requires-Dist: sphinxcontrib-qthelp (==1.0.3) ; extra == 'docs'
Requires-Dist: sphinxcontrib-serializinghtml (==1.1.4) ; extra == 'docs'
Requires-Dist: sphinxcontrib-tikz (==0.4.8) ; extra == 'docs'
Requires-Dist: sphinxcontrib-websupport (==1.2.2) ; extra == 'docs'
Requires-Dist: numpydoc (==0.9.2) ; extra == 'docs'
